galaxysprite/__init__.py
galaxysprite/src/__init__.py
galaxysprite/src/compressor.py
galaxysprite/src/density.py
galaxysprite/src/galactic.py
galaxysprite/src/main.py
galaxysprite-0.0.2.dist-info/LICENSE
galaxysprite-0.0.2.dist-info/METADATA
galaxysprite-0.0.2.dist-info/WHEEL
galaxysprite-0.0.2.dist-info/top_level.txt
galaxysprite-0.0.2.dist-info/RECORD
