Metadata-Version: 2.1
Name: galaxysprite
Version: 0.0.2
Summary: galaxysprite: make gifs!
Home-page: https://github.com/arixena24/galaxysprite
Author: Ariel Elizabeth Eunhee
Author-email: 
License: 
License-File: LICENSE
Requires-Dist: numpy
Requires-Dist: matplotlib
Requires-Dist: scipy
Requires-Dist: astropy
Requires-Dist: ffmpeg
